{"instance": "models/slipgrid/dummy.nm", "Type": "prMC", "Formula": "Rmin=? [F \"goal\"]", "Engine": "spsolve", "States": 14, "Transitions": 27, "Parameters": 5, "Solution": 55.193207, "Model instantiate [s]": 0.002605, "Model verify [s]": 0.051424, "Num. derivatives": 4, "LP (define matrices) [s]": 0.00309, "LP (solve) [s]": 0.006491, "Max. derivatives": [-2.736183, -0.069099, -0.163389, -0.019686], "Argmax. derivatives": ["param1", "param2", "param3", "param4"], "Max. validation": [-2.692351, -0.068984, -0.162543, -0.019631], "Difference %": [-0.01602, -0.001674, -0.005178, -0.002822]}